pyvenafi/__init__.py
pyvenafi/cloud/__init__.py
pyvenafi/cloud/api/__init__.py
pyvenafi/cloud/api/api_base.py
pyvenafi/cloud/api/authenticate.py
pyvenafi/cloud/api/cloud_api.py
pyvenafi/cloud/api/endpoints/__init__.py
pyvenafi/cloud/api/endpoints/account_service.py
pyvenafi/cloud/api/endpoints/activitylog_service.py
pyvenafi/cloud/api/endpoints/caoperations_service.py
pyvenafi/cloud/api/endpoints/certificate_service.py
pyvenafi/cloud/api/endpoints/connectors_service.py
pyvenafi/cloud/api/endpoints/edgemanagement_service.py
pyvenafi/cloud/api/endpoints/integrations_service.py
pyvenafi/cloud/api/endpoints/outagedetection_service.py
pyvenafi/cloud/api/endpoints/provisioning_service.py
pyvenafi/cloud/api/endpoints/tagging_service.py
pyvenafi/cloud/api/endpoints/vcamanagement_service.py
pyvenafi/cloud/api/enums/__init__.py
pyvenafi/cloud/api/models/__init__.py
pyvenafi/cloud/api/models/account_service.py
pyvenafi/cloud/api/models/activitylog_service.py
pyvenafi/cloud/api/models/caoperations_service.py
pyvenafi/cloud/api/models/certificate_service.py
pyvenafi/cloud/api/models/connectors_service.py
pyvenafi/cloud/api/models/edgemanagement_service.py
pyvenafi/cloud/api/models/integrations_service.py
pyvenafi/cloud/api/models/outagedetection_service.py
pyvenafi/cloud/api/models/provisioning_service.py
pyvenafi/cloud/api/models/tagging_service.py
pyvenafi/cloud/api/models/vcamanagement_service.py
pyvenafi/cloud/api/session.py
pyvenafi/cloud/attributes/__init__.py
pyvenafi/cloud/attributes/_helper.py
pyvenafi/cloud/features/__init__.py
pyvenafi/cloud/features/bases/__init__.py
pyvenafi/cloud/features/bases/feature_base.py
pyvenafi/cloud/features/definitions/__init__.py
pyvenafi/cloud/features/definitions/attribute_values.py
pyvenafi/cloud/features/definitions/attributes.py
pyvenafi/cloud/features/definitions/classes.py
pyvenafi/cloud/features/definitions/exceptions.py
pyvenafi/cloud/features/definitions/features.py
pyvenafi/logger.py
pyvenafi/tpp/__init__.py
pyvenafi-1.1.0.dist-info/LICENSE
pyvenafi-1.1.0.dist-info/METADATA
pyvenafi-1.1.0.dist-info/WHEEL
pyvenafi-1.1.0.dist-info/RECORD
