Metadata-Version: 2.3
Name: pyvenafi
Version: 1.1.0
Summary: Venafi TPP & Cloud API In Python
Author: SPI Team
Author-email: spi@venafi.com
Requires-Python: >=3.11,<4.0
Classifier: Programming Language :: Python :: 3
Classifier: Programming Language :: Python :: 3.11
Classifier: Programming Language :: Python :: 3.12
Classifier: Programming Language :: Python :: 3.13
Requires-Dist: isodate (>=0.6.0)
Requires-Dist: jsonpickle (>=2.1.0)
Requires-Dist: packaging (>=21.3)
Requires-Dist: pydantic (>=2.11,<3.0)
Requires-Dist: python-dateutil (>=2.8.2)
Requires-Dist: requests (>=2.24.0)
Requires-Dist: simplejson (>=3.17.6)
Project-URL: Repository, https://github.com/Venafi/pyVenafi
